<?xml version="1.0" encoding="UTF-8" ?>
<!DOCTYPE mapper PUBLIC "-//mybatis.org//DTD Mapper 3.0//EN" "http://mybatis.org/dtd/mybatis-3-mapper.dtd">

<mapper namespace="com.algotalk.communityservice.repository.ICommunityLikeScrapMapper">

    <!-- 좋아요 조회 -->
    <select id="getLike" parameterType="LikeScrapCommand" resultType="LikeScrapCommand">
        SELECT
            POST_ID    AS postId,
            USER_ID    AS userId,
            DELETED_YN AS deletedYn
        FROM COMMUNITY_LIKE
        WHERE POST_ID = #{postId}
          AND USER_ID = #{userId}
    </select>

    <!-- 좋아요 등록 -->
    <insert id="insertLike" parameterType="LikeScrapCommand">
        INSERT INTO COMMUNITY_LIKE (
            POST_ID,
            USER_ID,
            DELETED_YN,
            CREATED_AT,
            CREATED_BY,
            UPDATED_AT,
            UPDATED_BY
        ) VALUES (
                     #{postId},
                     #{userId},
                     'N',
                     NOW(),
                     #{userId},
                     NOW(),
                     #{userId}
                 )
    </insert>

    <!-- 좋아요 토글 -->
    <update id="toggleLike" parameterType="LikeScrapCommand">
        UPDATE COMMUNITY_LIKE
        SET
            DELETED_YN = #{deletedYn},
            UPDATED_AT = NOW(),
            UPDATED_BY = #{userId}
        WHERE POST_ID = #{postId}
          AND USER_ID = #{userId}
    </update>

    <!-- 스크랩 조회 -->
    <select id="getScrap" parameterType="LikeScrapCommand" resultType="LikeScrapCommand">
        SELECT
            POST_ID    AS postId,
            USER_ID    AS userId,
            DELETED_YN AS deletedYn
        FROM COMMUNITY_SCRAP
        WHERE POST_ID = #{postId}
          AND USER_ID = #{userId}
    </select>

    <!-- 스크랩 등록 -->
    <insert id="insertScrap" parameterType="LikeScrapCommand">
        INSERT INTO COMMUNITY_SCRAP (
            POST_ID,
            USER_ID,
            DELETED_YN,
            CREATED_AT,
            CREATED_BY,
            UPDATED_AT,
            UPDATED_BY
        ) VALUES (
                     #{postId},
                     #{userId},
                     'N',
                     NOW(),
                     #{userId},
                     NOW(),
                     #{userId}
                 )
    </insert>

    <!-- 스크랩 토글 -->
    <update id="toggleScrap" parameterType="LikeScrapCommand">
        UPDATE COMMUNITY_SCRAP
        SET
            DELETED_YN = #{deletedYn},
            UPDATED_AT = NOW(),
            UPDATED_BY = #{userId}
        WHERE POST_ID = #{postId}
          AND USER_ID = #{userId}
    </update>

    <!-- 좋아요 수 조회 (DB) -->
    <select id="getLikeCountFromDB" parameterType="LikeScrapCommand" resultType="Long">
        SELECT COUNT(*)
        FROM COMMUNITY_LIKE
        WHERE POST_ID  = #{postId}
          AND DELETED_YN = 'N'
    </select>

    <!-- 스크랩 수 조회 (DB) -->
    <select id="getScrapCountFromDB" parameterType="LikeScrapCommand" resultType="Long">
        SELECT COUNT(*)
        FROM COMMUNITY_SCRAP
        WHERE POST_ID  = #{postId}
          AND DELETED_YN = 'N'
    </select>

</mapper>